metabase_client/__init__.py
metabase_client/client.py
metabase_client/exceptions.py
metabase_client/http.py
metabase_client/resources.py
metabasepy/__init__.py
metabasepy/client.py
metabasepy/exceptions.py
metabasepy/http.py
metabasepy/resources.py
metabase_client-1.0.0.dist-info/LICENSE
metabase_client-1.0.0.dist-info/METADATA
metabase_client-1.0.0.dist-info/WHEEL
metabase_client-1.0.0.dist-info/top_level.txt
metabase_client-1.0.0.dist-info/RECORD
