Metadata-Version: 2.1
Name: metabase-client
Version: 1.0.0
Summary: A production-ready metabase client to spare you from handling HTTP requests directly
Home-page: https://github.com/Onyo/metabase_client
Author: Victor Martinez
Author-email: vcrmartinez@gmail.com
License: MIT
Keywords: metabase client api wrapper
Platform: UNKNOWN
Classifier: Intended Audience :: Developers
Classifier: Topic :: Utilities
Classifier: License :: Public Domain
Classifier: Natural Language :: English
Classifier: Operating System :: OS Independent
Classifier: Programming Language :: Python :: 3
Classifier: Programming Language :: Python :: 3.5
Classifier: Programming Language :: Python :: 3.6
Classifier: Programming Language :: Python :: 3.7
Classifier: Programming Language :: Python :: 3.8
Requires-Python: >=3.5
Requires-Dist: requests (==2.22.0)
